[
  {
    "county_slug": "fond du lac",
    "state": "WI",
    "verified": false,
    "name": "Barlow Park",
    "description": "Come play pickleball at Barlow Park in Ripon, WI! There are 2 outdoor hard courts. The lines are permanent, but you'll need to bring your own net. The courts are free.",
    "address": "1052 Newbury St",
    "city": "Ripon",
    "latitude": 43.831705,
    "longitude": -88.83791,
    "indoor": false,
    "num_courts": 2,
    "surface_type": "Hard",
    "fees": "Free",
    "phone": "+19207484909",
    "website": "https://www.valuworld.com/usa/wi/supermall/County/FondDuLac/ripon/riponparks/parks.htm",
    "photo_url": "https://cdn.filestackcontent.com/Q2Rb5OJMTkawAjPexexo",
    "nets_provided": false,
    "skill_levels": "beginner,intermediate",
    "court_type": "dedicated",
    "has_restrooms": true
  },
  {
    "county_slug": "fond du lac",
    "state": "WI",
    "verified": false,
    "name": "Fond Du Lac YMCA",
    "description": "Fond Du Lac YMCA is one of the most popular places to play pickleball in Fond du Lac, WI. There are 2 indoor hard courts. The lines are permanent, and portable nets are available. A membership is required to play. The facility includes amenities like restrooms.",
    "address": "90 W 2nd St",
    "city": "Fond du Lac",
    "latitude": 43.774843,
    "longitude": -88.450538,
    "indoor": true,
    "num_courts": 2,
    "surface_type": "Hard",
    "fees": "Members only",
    "phone": "+19209213330",
    "website": "https://www.fdlymca.org/",
    "photo_url": "https://cdn.filestackcontent.com/0UAMMZNSjifrRDD0an6g",
    "has_restrooms": true,
    "nets_provided": true,
    "skill_levels": "advanced,beginner,intermediate",
    "court_type": "dedicated",
    "hours": "Sun 5am - 8:30 pm"
  },
  {
    "county_slug": "fond du lac",
    "state": "WI",
    "verified": false,
    "name": "Horace Mann High School",
    "description": "Six courts with permanent nets. Bring your own nets to play on the tennis court.",
    "address": "325 McKinley St",
    "city": "North Fond du Lac",
    "zip_code": "54937",
    "latitude": 43.812413,
    "longitude": -88.487494,
    "indoor": false,
    "num_courts": 8,
    "surface_type": "Asphalt",
    "open_play_schedule": "Can only play when school is not in session",
    "fees": "Free",
    "phone": "9209603475",
    "photo_url": "https://cdn.filestackcontent.com/ZdZTq8sRyaTCuTFXBCUS",
    "has_restrooms": true,
    "wheelchair_accessible": true,
    "nets_provided": true,
    "skill_levels": "beginner,intermediate",
    "court_type": "dedicated"
  },
  {
    "county_slug": "fond du lac",
    "state": "WI",
    "verified": false,
    "name": "Ripon Area School District Courts",
    "description": "Ripon Area School District Courts is one of the most popular places to play pickleball in Ripon, WI. There are 8 outdoor asphalt courts. The lines are overlaid on a tennis court, so the net is a little taller than a normal pickleball net. The courts are free.",
    "address": "St Wenceslaus St",
    "city": "Ripon",
    "latitude": 43.839173,
    "longitude": -88.833565,
    "indoor": false,
    "num_courts": 8,
    "surface_type": "Asphalt",
    "fees": "Free",
    "phone": "9205853120",
    "skill_levels": "intermediate",
    "court_type": "dedicated"
  },
  {
    "county_slug": "fond du lac",
    "state": "WI",
    "verified": false,
    "name": "Ripon College Thorne Street Courts",
    "description": "Ripon College Thorne Street Courts is one of the most popular places to play pickleball in Ripon, WI. There are 6 outdoor hard courts. The lines are permanent, but you'll need to bring your own net. A membership is required to play.",
    "address": "715 W Thorne St",
    "city": "Ripon",
    "latitude": 43.841088,
    "longitude": -88.849265,
    "indoor": false,
    "num_courts": 6,
    "surface_type": "Hard",
    "fees": "Members only",
    "website": "https://ripon.edu/2020/10/30/virtual-art-exhibit-will-feature-images-of-longing-loss-in-midwestern-cities/",
    "photo_url": "https://cdn.filestackcontent.com/2oyfoVbQVqirJfiNMklj",
    "nets_provided": false,
    "skill_levels": "beginner,intermediate",
    "court_type": "dedicated",
    "has_parking": true
  },
  {
    "county_slug": "fond du lac",
    "state": "WI",
    "verified": false,
    "name": "Taylor Park",
    "description": "Taylor Park is one of the most popular places to play pickleball in Fond du Lac, WI. There are 3 outdoor concrete courts. These are dedicated courts with permanent lines and nets. You can reserve the courts. The courts are free. Amenities include restrooms and water.",
    "address": "115 South Hickory Street",
    "city": "Fond du Lac",
    "latitude": 43.775129,
    "longitude": -88.460373,
    "indoor": false,
    "num_courts": 3,
    "surface_type": "Concrete",
    "fees": "Free",
    "phone": "+19203223955",
    "website": "https://friendsoftaylorparkandpool.com/taylor-park-pool/",
    "photo_url": "https://cdn.filestackcontent.com/rIZYsMmSRnKmbQZvHdIm",
    "has_restrooms": true,
    "has_water": true,
    "nets_provided": true,
    "skill_levels": "beginner,intermediate",
    "court_type": "dedicated"
  }
]